{
  "Version": 3,
  "Meta": {
    "Duration": 0.7,
    "Fps": 30,
    "Loop": false,
    "AreBeziersRestricted": true,
    "CurveCount": 6,
    "TotalSegmentCount": 24,
    "TotalPointCount": 30,
    "UserDataCount": 0,
    "TotalUserDataSize": 0
  },
  "Curves": [
    { "Target": "Parameter", "Id": "ParamAngleX", "Segments": [0, 0, 0, 0.12, -7, 0, 0.26, 7, 0, 0.46, -5, 0, 0.7, 0] },
    { "Target": "Parameter", "Id": "ParamAngleZ", "Segments": [0, 0, 0, 0.12, -8, 0, 0.26, 8, 0, 0.46, -6, 0, 0.7, 0] },
    { "Target": "Parameter", "Id": "ParamBodyAngleZ", "Segments": [0, 0, 0, 0.12, -4, 0, 0.26, 4, 0, 0.46, -3, 0, 0.7, 0] },
    { "Target": "Parameter", "Id": "ParamArms", "Segments": [0, 0.18, 0, 0.12, 0.44, 0, 0.26, 0.28, 0, 0.46, 0.5, 0, 0.7, 0.18] },
    { "Target": "Parameter", "Id": "Param_Angle_Rotation10", "Segments": [0, 0, 0, 0.12, 12, 0, 0.26, -8, 0, 0.46, 10, 0, 0.7, 0] },
    { "Target": "Parameter", "Id": "Param_Angle_Rotation12", "Segments": [0, 0, 0, 0.12, -12, 0, 0.26, 8, 0, 0.46, -10, 0, 0.7, 0] }
  ]
}
